pypomes_crypto/__init__.py
pypomes_crypto/cert_pomes.py
pypomes_crypto/crypto_aes.py
pypomes_crypto/crypto_base.py
pypomes_crypto/crypto_common.py
pypomes_crypto/crypto_pdf.py
pypomes_crypto/crypto_pkcs7.py
pypomes_crypto/crypto_pomes.py
pypomes_crypto/jwt_pomes.py
pypomes_crypto-0.8.7.dist-info/METADATA
pypomes_crypto-0.8.7.dist-info/WHEEL
pypomes_crypto-0.8.7.dist-info/licenses/LICENSE
pypomes_crypto-0.8.7.dist-info/RECORD
