Metadata-Version: 2.4
Name: pypomes_crypto
Version: 0.8.7
Summary: A collection of Python pomes, penyeach (cryptography modules)
Project-URL: Homepage, https://github.com/TheWiseCoder/PyPomes-Crypto
Project-URL: Bug Tracker, https://github.com/TheWiseCoder/PyPomes-Crypto/issues
Author-email: GT Nunes <wisecoder01@gmail.com>
License-File: LICENSE
Classifier: License :: OSI Approved :: MIT License
Classifier: Operating System :: OS Independent
Classifier: Programming Language :: Python :: 3
Requires-Python: >=3.14
Requires-Dist: argon2-cffi>=25.1.0
Requires-Dist: asn1crypto>=1.5.1
Requires-Dist: cryptography>=46.0.3
Requires-Dist: passlib>=1.7.4
Requires-Dist: pycryptodome>=3.23.0
Requires-Dist: pyhanko>=0.32.0
Requires-Dist: pyjwt>=2.10.1
Requires-Dist: pypdf2>=3.0.1
Requires-Dist: pypomes-core>=3.0.8
Requires-Dist: requests>=2.32.5
